xevel/__init__.py
xevel/xevel.py
Xevel-0.4.4.dist-info/METADATA
Xevel-0.4.4.dist-info/WHEEL
Xevel-0.4.4.dist-info/top_level.txt
Xevel-0.4.4.dist-info/RECORD
