Metadata-Version: 2.1
Name: Xevel
Version: 0.4.4
Summary: Python ASGI server
Home-page: https://github.com/tsunyoku/Xevel
Author: tsunyoku
Author-email: tsunyoku@gmail.com
License: UNKNOWN
Platform: UNKNOWN
Classifier: Programming Language :: Python :: 3
Classifier: License :: OSI Approved :: MIT License
Classifier: Operating System :: OS Independent
Requires-Python: >=3.8
